{"type":"node","id":"1","labels":["personality"],"properties":{"name":"ope-high"}}
{"type":"node","id":"2","labels":["personality"],"properties":{"name":"ext-avg"}}
{"type":"node","id":"24","labels":["description"],"properties":{"name":"introspection"}}
{"type":"node","id":"25","labels":["word"],"properties":{"name":"diff-verb-"}}
{"type":"node","id":"26","labels":["word"],"properties":{"name":"usual-adverb-"}}
{"type":"node","id":"27","labels":["word"],"properties":{"name":"achievement+"}}
{"type":"node","id":"28","labels":["word"],"properties":{"name":"belonging-"}}
{"type":"node","id":"29","labels":["word"],"properties":{"name":"belonging+"}}
{"type":"node","id":"90","labels":["personality"],"properties":{"name":"ope-avg"}}
{"type":"node","id":"91","labels":["personality"],"properties":{"name":"ope-low"}}
{"type":"node","id":"92","labels":["personality"],"properties":{"name":"con-low"}}
{"type":"node","id":"93","labels":["personality"],"properties":{"name":"con-avg"}}
{"type":"node","id":"94","labels":["personality"],"properties":{"name":"ext-high"}}
{"type":"node","id":"95","labels":["personality"],"properties":{"name":"agr-avg"}}
{"type":"node","id":"96","labels":["personality"],"properties":{"name":"agr-low"}}
{"type":"node","id":"97","labels":["personality"],"properties":{"name":"neu-low"}}
{"type":"node","id":"181","labels":["personality"],"properties":{"name":"con-high"}}
{"type":"node","id":"182","labels":["personality"],"properties":{"name":"ext-low"}}
{"type":"node","id":"347988","labels":["personality"],"properties":{"name":"con"}}
{"type":"node","id":"347989","labels":["personality"],"properties":{"name":"agr-high"}}
{"type":"node","id":"347990","labels":["personality"],"properties":{"name":"neu-avg"}}
{"type":"node","id":"347991","labels":["personality"],"properties":{"name":"neu-high"}}
{"type":"node","id":"358941","labels":["word"],"properties":{"name":"I+"}}
{"type":"node","id":"358942","labels":["people"],"properties":{"name":"politician"}}
{"type":"node","id":"358950","labels":["personality"],"properties":{"name":"ope"}}
{"type":"node","id":"358951","labels":["personality"],"properties":{"name":"neu"}}
{"type":"node","id":"384441","labels":["word"],"properties":{"name":"we+"}}
{"type":"node","id":"384442","labels":["word"],"properties":{"name":"you+"}}
{"type":"node","id":"384443","labels":["word"],"properties":{"name":"he+"}}
{"type":"node","id":"384444","labels":["word"],"properties":{"name":"they+"}}
{"type":"node","id":"384445","labels":["word"],"properties":{"name":"pronoun+"}}
{"type":"node","id":"384446","labels":["word"],"properties":{"name":"article+"}}
{"type":"node","id":"384447","labels":["word"],"properties":{"name":"prep+"}}
{"type":"node","id":"384448","labels":["word"],"properties":{"name":"future-tense+"}}
{"type":"node","id":"384449","labels":["word"],"properties":{"name":"now-tense+"}}
{"type":"node","id":"384450","labels":["word"],"properties":{"name":"past-tense+"}}
{"type":"node","id":"384451","labels":["word"],"properties":{"name":"punctuation+"}}
{"type":"node","id":"384452","labels":["word"],"properties":{"name":"big-word+"}}
{"type":"node","id":"384453","labels":["word"],"properties":{"name":"pos-emotion+"}}
{"type":"node","id":"384454","labels":["word"],"properties":{"name":"neg-emotion+"}}
{"type":"node","id":"384455","labels":["word"],"properties":{"name":"cognition+"}}
{"type":"node","id":"384456","labels":["word"],"properties":{"name":"causality+"}}
{"type":"node","id":"384457","labels":["word"],"properties":{"name":"noun+"}}
{"type":"node","id":"384458","labels":["word"],"properties":{"name":"social+"}}
{"type":"node","id":"401394","labels":["word"],"properties":{"name":"I-"}}
{"type":"node","id":"401395","labels":["word"],"properties":{"name":"we-"}}
{"type":"node","id":"401396","labels":["word"],"properties":{"name":"you-"}}
{"type":"node","id":"401397","labels":["word"],"properties":{"name":"he-"}}
{"type":"node","id":"401398","labels":["word"],"properties":{"name":"they-"}}
{"type":"node","id":"436987","labels":["personality"],"properties":{"name":"ext"}}
{"type":"node","id":"439224","labels":["personality"],"properties":{"name":"agr"}}
{"type":"node","id":"442538","labels":["people"],"properties":{"name":"suspect"}}
{"type":"node","id":"442539","labels":["description","people"],"properties":{"name":"team-identity"}}
{"type":"node","id":"442541","labels":["description"],"properties":{"name":"organized"}}
{"type":"node","id":"442543","labels":["word"],"properties":{"name":"insight-"}}
{"type":"node","id":"442546","labels":["word"],"properties":{"name":"achievement-"}}
{"type":"node","id":"442547","labels":["word"],"properties":{"name":"power+"}}
{"type":"node","id":"442548","labels":["word"],"properties":{"name":"power-"}}
{"type":"node","id":"442549","labels":["emotion"],"properties":{"name":"negative-emotion"}}
{"type":"node","id":"442558","labels":["description"],"properties":{"name":"confidence"}}
{"type":"node","id":"442559","labels":["people"],"properties":{"name":"male"}}
{"type":"node","id":"442560","labels":["people"],"properties":{"name":"female"}}
{"type":"node","id":"442561","labels":["description"],"properties":{"name":"cautious"}}
{"type":"node","id":"442562","labels":["people"],"properties":{"name":"old"}}
{"type":"node","id":"442563","labels":["people"],"properties":{"name":"young"}}
{"type":"node","id":"442565","labels":["word"],"properties":{"name":"usual-adverb+"}}
{"type":"node","id":"442566","labels":["description"],"properties":{"name":"humor"}}
{"type":"node","id":"442567","labels":["description"],"properties":{"name":"cognitive"}}
{"type":"node","id":"442568","labels":["word"],"properties":{"name":"insight+"}}
{"type":"node","id":"442570","labels":["word"],"properties":{"name":"pronoun-"}}
{"type":"node","id":"442571","labels":["word"],"properties":{"name":"article-"}}
{"type":"node","id":"442572","labels":["word"],"properties":{"name":"prep-"}}
{"type":"node","id":"442573","labels":["word"],"properties":{"name":"future-tense-"}}
{"type":"node","id":"442574","labels":["word"],"properties":{"name":"now-tense-"}}
{"type":"node","id":"442575","labels":["word"],"properties":{"name":"past-tense-"}}
{"type":"node","id":"442576","labels":["word"],"properties":{"name":"punctuation-"}}
{"type":"node","id":"442577","labels":["word"],"properties":{"name":"big-word-"}}
{"type":"node","id":"442578","labels":["word"],"properties":{"name":"pos-emotion-"}}
{"type":"node","id":"442579","labels":["word"],"properties":{"name":"neg-emotion-"}}
{"type":"node","id":"442580","labels":["word"],"properties":{"name":"cognition-"}}
{"type":"node","id":"442581","labels":["word"],"properties":{"name":"causality-"}}
{"type":"node","id":"442582","labels":["word"],"properties":{"name":"noun-"}}
{"type":"node","id":"442583","labels":["word"],"properties":{"name":"social-"}}
{"type":"node","id":"442584","labels":["word"],"properties":{"name":"verb-"}}
{"type":"node","id":"442585","labels":["word"],"properties":{"name":"modal-verb-"}}
{"type":"node","id":"442586","labels":["word"],"properties":{"name":"aux-verb-"}}
{"type":"node","id":"442587","labels":["word"],"properties":{"name":"noun-group-"}}
{"type":"node","id":"442588","labels":["word"],"properties":{"name":"proverb-group-"}}
{"type":"node","id":"442589","labels":["word"],"properties":{"name":"negate-"}}
{"type":"node","id":"442590","labels":["word"],"properties":{"name":"verb+"}}
{"type":"node","id":"442591","labels":["word"],"properties":{"name":"modal-verb+"}}
{"type":"node","id":"442592","labels":["word"],"properties":{"name":"aux-verb+"}}
{"type":"node","id":"442593","labels":["word"],"properties":{"name":"noun-group+"}}
{"type":"node","id":"442594","labels":["word"],"properties":{"name":"proverb-group+"}}
{"type":"node","id":"442595","labels":["word"],"properties":{"name":"negate+"}}
{"type":"node","id":"442596","labels":["word"],"properties":{"name":"except+"}}
{"type":"node","id":"442597","labels":["word"],"properties":{"name":"assumption+"}}
{"type":"node","id":"442598","labels":["word"],"properties":{"name":"certainty+"}}
{"type":"node","id":"442599","labels":["word"],"properties":{"name":"det+"}}
{"type":"node","id":"442600","labels":["word"],"properties":{"name":"conj+"}}
{"type":"node","id":"442601","labels":["word"],"properties":{"name":"concrete-noun+"}}
{"type":"node","id":"442602","labels":["word"],"properties":{"name":"time+"}}
{"type":"node","id":"442603","labels":["word"],"properties":{"name":"space+"}}
{"type":"node","id":"442604","labels":["word"],"properties":{"name":"numeric+"}}
{"type":"node","id":"442605","labels":["word"],"properties":{"name":"behave-sen+"}}
{"type":"node","id":"442606","labels":["word"],"properties":{"name":"long-sen+"}}
{"type":"node","id":"442607","labels":["word"],"properties":{"name":"fuck-word+"}}
{"type":"node","id":"442610","labels":["word"],"properties":{"name":"except-"}}
{"type":"node","id":"442611","labels":["word"],"properties":{"name":"assumption-"}}
{"type":"node","id":"442612","labels":["word"],"properties":{"name":"certainty-"}}
{"type":"node","id":"442613","labels":["word"],"properties":{"name":"det-"}}
{"type":"node","id":"442614","labels":["word"],"properties":{"name":"conj-"}}
{"type":"node","id":"442615","labels":["word"],"properties":{"name":"concrete-noun-"}}
{"type":"node","id":"442616","labels":["word"],"properties":{"name":"time-"}}
{"type":"node","id":"442617","labels":["word"],"properties":{"name":"space-"}}
{"type":"node","id":"442618","labels":["word"],"properties":{"name":"numeric-"}}
{"type":"node","id":"442619","labels":["word"],"properties":{"name":"behave-sen-"}}
{"type":"node","id":"442620","labels":["word"],"properties":{"name":"long-sen-"}}
{"type":"node","id":"442621","labels":["word"],"properties":{"name":"fuck-word-"}}
{"type":"node","id":"442624","labels":["social-status"],"properties":{"name":"low-social-status"}}
{"type":"node","id":"442625","labels":["mental-state"],"properties":{"name":"mental-unhealthy"}}
{"type":"node","id":"442626","labels":["need"],"properties":{"name":"power"}}
{"type":"node","id":"442627","labels":["think-style"],"properties":{"name":"classification"}}
{"type":"node","id":"442628","labels":["think-style"],"properties":{"name":"causality-think"}}
{"type":"node","id":"442629","labels":["think-style"],"properties":{"name":"complicated"}}
{"type":"node","id":"442630","labels":["social-status"],"properties":{"name":"high-social-status"}}
{"type":"node","id":"442631","labels":["mental-state"],"properties":{"name":"mental-healthy"}}
{"type":"node","id":"442632","labels":["need"],"properties":{"name":"achievement"}}
{"type":"node","id":"442633","labels":["need"],"properties":{"name":"belonging"}}
{"type":"node","id":"442634","labels":["think-style"],"properties":{"name":"dynamic"}}
{"type":"node","id":"442635","labels":["think-style"],"properties":{"name":"non-causality-think"}}
{"type":"node","id":"442636","labels":["think-style"],"properties":{"name":"simple"}}
{"type":"node","id":"442637","labels":["write-style"],"properties":{"name":"narrative"}}
{"type":"node","id":"442638","labels":["emotion"],"properties":{"name":"happiness"}}
{"type":"node","id":"442639","labels":["emotion"],"properties":{"name":"angry"}}
{"type":"node","id":"442640","labels":["team-identity"],"properties":{"name":"prejudice"}}
{"type":"node","id":"442641","labels":["description"],"properties":{"name":"leadership"}}
{"type":"node","id":"442642","labels":["description"],"properties":{"name":"powerful"}}
{"type":"node","id":"442643","labels":["description"],"properties":{"name":"political"}}
{"type":"node","id":"442644","labels":["description"],"properties":{"name":"self-attention"}}
{"type":"node","id":"442645","labels":["description"],"properties":{"name":"depressed"}}
{"type":"node","id":"442646","labels":["description"],"properties":{"name":"artistic"}}
{"type":"node","id":"442647","labels":["description"],"properties":{"name":"high-spirited"}}
{"type":"node","id":"442648","labels":["description"],"properties":{"name":"open"}}
{"type":"node","id":"442649","labels":["description"],"properties":{"name":"reminiscence"}}
{"type":"node","id":"442650","labels":["write-style"],"properties":{"name":"formality"}}
{"type":"node","id":"442651","labels":["write-style"],"properties":{"name":"analytical"}}
{"type":"node","id":"442652","labels":["emotion"],"properties":{"name":"sadness"}}
{"type":"node","id":"442653","labels":["team-identity"],"properties":{"name":"modeled"}}
{"type":"node","id":"442654","labels":["team-identity"],"properties":{"name":"discriminate"}}
{"type":"node","id":"442655","labels":["description"],"properties":{"name":"arrogance"}}
{"type":"node","id":"442657","labels":["description"],"properties":{"name":"indifference"}}
{"type":"node","id":"442658","labels":["description"],"properties":{"name":"lack-of-safety"}}
{"type":"node","id":"442659","labels":["description"],"properties":{"name":"anxiety"}}
{"type":"node","id":"442660","labels":["description"],"properties":{"name":"sociability"}}
{"type":"node","id":"442661","labels":["description"],"properties":{"name":"outgoing"}}
{"type":"node","id":"442662","labels":["description"],"properties":{"name":"warm"}}
{"type":"node","id":"442663","labels":["description"],"properties":{"name":"conservative"}}
{"type":"node","id":"442664","labels":["description"],"properties":{"name":"steady"}}
{"type":"node","id":"442665","labels":["description"],"properties":{"name":"hypocritical"}}
{"type":"node","id":"442666","labels":["description"],"properties":{"name":"shirk-duty"}}
{"type":"node","id":"442670","labels":["description"],"properties":{"name":"rigid"}}
{"type":"node","id":"442671","labels":["description"],"properties":{"name":"honest"}}
{"type":"node","id":"442672","labels":["description"],"properties":{"name":"innocent"}}
{"type":"node","id":"442690","labels":["description"],"properties":{"name":"evolutive"}}
{"type":"node","id":"442691","labels":["description"],"properties":{"name":"unsteady"}}
{"type":"node","id":"442692","labels":["people"],"properties":{"name":"truth"}}
{"type":"node","id":"442696","labels":["word"],"properties":{"name":"no-doubt+"}}
{"type":"node","id":"442697","labels":["word"],"properties":{"name":"possibly+"}}
{"type":"node","id":"442710","labels":["people"],"properties":{"name":"depression"}}
{"type":"node","id":"442711","labels":["people"],"properties":{"name":"lier"}}
{"type":"node","id":"442714","labels":["word"],"properties":{"name":"diff-verb+"}}
{"type":"node","id":"442715","labels":["word"],"properties":{"name":"phrase+"}}
{"type":"node","id":"442716","labels":["description"],"properties":{"name":"indecision"}}
{"id":"0","type":"relationship","label":"USE","start":{"id":"442652","labels":["emotion"]},"end":{"id":"358941","labels":["word"]}}
{"id":"20","type":"relationship","label":"USE","start":{"id":"442560","labels":["people"]},"end":{"id":"358941","labels":["word"]}}
{"id":"40","type":"relationship","label":"CONTAIN","start":{"id":"442593","labels":["word"]},"end":{"id":"384447","labels":["word"]}}
{"id":"41","type":"relationship","label":"CONTAIN","start":{"id":"442593","labels":["word"]},"end":{"id":"384452","labels":["word"]}}
{"id":"42","type":"relationship","label":"USE","start":{"id":"442692","labels":["people"]},"end":{"id":"442602","labels":["word"]}}
{"id":"43","type":"relationship","label":"CONTAIN","start":{"id":"442593","labels":["word"]},"end":{"id":"384457","labels":["word"]}}
{"id":"44","type":"relationship","label":"CONTAIN","start":{"id":"442594","labels":["word"]},"end":{"id":"358941","labels":["word"]}}
{"id":"45","type":"relationship","label":"USE","start":{"id":"442559","labels":["people"]},"end":{"id":"442593","labels":["word"]}}
{"id":"46","type":"relationship","label":"USE","start":{"id":"442624","labels":["social-status"]},"end":{"id":"442594","labels":["word"]}}
{"id":"47","type":"relationship","label":"USE","start":{"id":"442560","labels":["people"]},"end":{"id":"442594","labels":["word"]}}
{"id":"48","type":"relationship","label":"USE","start":{"id":"442562","labels":["people"]},"end":{"id":"442593","labels":["word"]}}
{"id":"49","type":"relationship","label":"CONTAIN","start":{"id":"442650","labels":["write-style"]},"end":{"id":"442574","labels":["word"]}}
{"id":"50","type":"relationship","label":"CONTAIN","start":{"id":"442650","labels":["write-style"]},"end":{"id":"25","labels":["word"]}}
{"id":"51","type":"relationship","label":"CONTAIN","start":{"id":"442650","labels":["write-style"]},"end":{"id":"26","labels":["word"]}}
{"id":"52","type":"relationship","label":"CONTAIN","start":{"id":"442650","labels":["write-style"]},"end":{"id":"384452","labels":["word"]}}
{"id":"53","type":"relationship","label":"CONTAIN","start":{"id":"442650","labels":["write-style"]},"end":{"id":"384446","labels":["word"]}}
{"id":"54","type":"relationship","label":"CONTAIN","start":{"id":"442650","labels":["write-style"]},"end":{"id":"442604","labels":["word"]}}
{"id":"55","type":"relationship","label":"IMPLY","start":{"id":"442650","labels":["write-style"]},"end":{"id":"442655","labels":["description"]}}
{"id":"56","type":"relationship","label":"IMPLY","start":{"id":"442650","labels":["write-style"]},"end":{"id":"442643","labels":["description"]}}
{"id":"57","type":"relationship","label":"lackOf","start":{"id":"442650","labels":["write-style"]},"end":{"id":"442566","labels":["description"]}}
{"id":"7448","type":"relationship","label":"USE","start":{"id":"442639","labels":["emotion"]},"end":{"id":"384442","labels":["word"]}}
{"id":"18352","type":"relationship","label":"USE","start":{"id":"442639","labels":["emotion"]},"end":{"id":"384449","labels":["word"]}}
{"id":"21639","type":"relationship","label":"CONTAIN","start":{"id":"442549","labels":["emotion"]},"end":{"id":"442652","labels":["emotion"]}}
{"id":"23876","type":"relationship","label":"BEING","start":{"id":"442549","labels":["emotion"]},"end":{"id":"442567","labels":["description"]}}
{"id":"31522","type":"relationship","label":"BEING","start":{"id":"442549","labels":["emotion"]},"end":{"id":"24","labels":["description"]}}
{"id":"50495","type":"relationship","label":"USE","start":{"id":"442628","labels":["think-style"]},"end":{"id":"442600","labels":["word"]}}
{"id":"56934","type":"relationship","label":"BEING","start":{"id":"442710","labels":["people"]},"end":{"id":"442659","labels":["description"]}}
{"id":"74352","type":"relationship","label":"USE","start":{"id":"442629","labels":["think-style"]},"end":{"id":"442602","labels":["word"]}}
{"id":"76830","type":"relationship","label":"NEED","start":{"id":"442547","labels":["word"]},"end":{"id":"442626","labels":["need"]}}
{"id":"96902","type":"relationship","label":"OPPOSITE","start":{"id":"442628","labels":["think-style"]},"end":{"id":"442635","labels":["think-style"]}}
{"id":"235512","type":"relationship","label":"USE","start":{"id":"442629","labels":["think-style"]},"end":{"id":"442606","labels":["word"]}}
{"id":"266939","type":"relationship","label":"USE","start":{"id":"442629","labels":["think-style"]},"end":{"id":"442603","labels":["word"]}}
{"id":"270392","type":"relationship","label":"USE","start":{"id":"442629","labels":["think-style"]},"end":{"id":"442600","labels":["word"]}}
{"id":"279733","type":"relationship","label":"USE","start":{"id":"442638","labels":["emotion"]},"end":{"id":"384441","labels":["word"]}}
{"id":"299102","type":"relationship","label":"USE","start":{"id":"442652","labels":["emotion"]},"end":{"id":"384450","labels":["word"]}}
{"id":"308354","type":"relationship","label":"USE","start":{"id":"442652","labels":["emotion"]},"end":{"id":"384448","labels":["word"]}}
{"id":"322770","type":"relationship","label":"USE","start":{"id":"442639","labels":["emotion"]},"end":{"id":"384443","labels":["word"]}}
{"id":"334302","type":"relationship","label":"USE","start":{"id":"442639","labels":["emotion"]},"end":{"id":"384444","labels":["word"]}}
{"id":"346076","type":"relationship","label":"CONTAIN","start":{"id":"442549","labels":["emotion"]},"end":{"id":"442639","labels":["emotion"]}}
{"id":"351103","type":"relationship","label":"USE","start":{"id":"442549","labels":["emotion"]},"end":{"id":"384455","labels":["word"]}}
{"id":"365080","type":"relationship","label":"USE","start":{"id":"442710","labels":["people"]},"end":{"id":"358941","labels":["word"]}}
{"id":"370281","type":"relationship","label":"USE","start":{"id":"442627","labels":["think-style"]},"end":{"id":"442601","labels":["word"]}}
{"id":"376215","type":"relationship","label":"USE","start":{"id":"442627","labels":["think-style"]},"end":{"id":"442586","labels":["word"]}}
{"id":"397467","type":"relationship","label":"BEING","start":{"id":"442710","labels":["people"]},"end":{"id":"442645","labels":["description"]}}
{"id":"401371","type":"relationship","label":"BEING","start":{"id":"442692","labels":["people"]},"end":{"id":"442672","labels":["description"]}}
{"id":"401372","type":"relationship","label":"BEING","start":{"id":"442711","labels":["people"]},"end":{"id":"442666","labels":["description"]}}
{"id":"401373","type":"relationship","label":"USE","start":{"id":"442711","labels":["people"]},"end":{"id":"442601","labels":["word"]}}
{"id":"405026","type":"relationship","label":"USE","start":{"id":"442711","labels":["people"]},"end":{"id":"442579","labels":["word"]}}
{"id":"410865","type":"relationship","label":"BEING","start":{"id":"442710","labels":["people"]},"end":{"id":"442646","labels":["description"]}}
{"id":"431860","type":"relationship","label":"BEING","start":{"id":"442710","labels":["people"]},"end":{"id":"442691","labels":["description"]}}
{"id":"435151","type":"relationship","label":"BEING","start":{"id":"442710","labels":["people"]},"end":{"id":"442652","labels":["emotion"]}}
{"id":"436961","type":"relationship","label":"BEING","start":{"id":"442692","labels":["people"]},"end":{"id":"442671","labels":["description"]}}
{"id":"442568","type":"relationship","label":"USE","start":{"id":"442711","labels":["people"]},"end":{"id":"401394","labels":["word"]}}
{"id":"442569","type":"relationship","label":"USE","start":{"id":"442711","labels":["people"]},"end":{"id":"442714","labels":["word"]}}
{"id":"442570","type":"relationship","label":"CONTAIN","start":{"id":"442715","labels":["word"]},"end":{"id":"442696","labels":["word"]}}
{"id":"442571","type":"relationship","label":"IMPLY","start":{"id":"442696","labels":["word"]},"end":{"id":"442655","labels":["description"]}}
{"id":"442572","type":"relationship","label":"USE","start":{"id":"442692","labels":["people"]},"end":{"id":"442603","labels":["word"]}}
{"id":"442573","type":"relationship","label":"USE","start":{"id":"442711","labels":["people"]},"end":{"id":"384443","labels":["word"]}}
{"id":"442574","type":"relationship","label":"USE","start":{"id":"442711","labels":["people"]},"end":{"id":"442605","labels":["word"]}}
{"id":"442575","type":"relationship","label":"BEING","start":{"id":"442539","labels":["description","people"]},"end":{"id":"442640","labels":["team-identity"]}}
{"id":"442576","type":"relationship","label":"CONTAIN","start":{"id":"442538","labels":["people"]},"end":{"id":"442692","labels":["people"]}}
{"id":"442577","type":"relationship","label":"CONTAIN","start":{"id":"442538","labels":["people"]},"end":{"id":"442711","labels":["people"]}}
{"id":"442578","type":"relationship","label":"BEING","start":{"id":"442711","labels":["people"]},"end":{"id":"442665","labels":["description"]}}
{"id":"442579","type":"relationship","label":"USE","start":{"id":"442711","labels":["people"]},"end":{"id":"442590","labels":["word"]}}
{"id":"442580","type":"relationship","label":"IMPLY","start":{"id":"358941","labels":["word"]},"end":{"id":"442644","labels":["description"]}}
{"id":"442581","type":"relationship","label":"BEING","start":{"id":"442560","labels":["people"]},"end":{"id":"442644","labels":["description"]}}
{"id":"442582","type":"relationship","label":"BEING","start":{"id":"442630","labels":["social-status"]},"end":{"id":"442641","labels":["description"]}}
{"id":"442583","type":"relationship","label":"USE","start":{"id":"442630","labels":["social-status"]},"end":{"id":"384441","labels":["word"]}}
{"id":"442584","type":"relationship","label":"USE","start":{"id":"442630","labels":["social-status"]},"end":{"id":"384442","labels":["word"]}}
{"id":"442585","type":"relationship","label":"IMPLY","start":{"id":"384441","labels":["word"]},"end":{"id":"442558","labels":["description"]}}
{"id":"442586","type":"relationship","label":"IMPLY","start":{"id":"384441","labels":["word"]},"end":{"id":"442641","labels":["description"]}}
{"id":"442587","type":"relationship","label":"IMPLY","start":{"id":"384441","labels":["word"]},"end":{"id":"442655","labels":["description"]}}
{"id":"442588","type":"relationship","label":"lackOf","start":{"id":"442697","labels":["word"]},"end":{"id":"442650","labels":["write-style"]}}
{"id":"442589","type":"relationship","label":"USE","start":{"id":"442692","labels":["people"]},"end":{"id":"442584","labels":["word"]}}
{"id":"442590","type":"relationship","label":"USE","start":{"id":"442692","labels":["people"]},"end":{"id":"358941","labels":["word"]}}
{"id":"442591","type":"relationship","label":"USE","start":{"id":"442692","labels":["people"]},"end":{"id":"442578","labels":["word"]}}
{"id":"442592","type":"relationship","label":"USE","start":{"id":"442692","labels":["people"]},"end":{"id":"442580","labels":["word"]}}
{"id":"442593","type":"relationship","label":"USE","start":{"id":"442711","labels":["people"]},"end":{"id":"442578","labels":["word"]}}
{"id":"442594","type":"relationship","label":"CONTAIN","start":{"id":"442715","labels":["word"]},"end":{"id":"442697","labels":["word"]}}
{"id":"442595","type":"relationship","label":"IMPLY","start":{"id":"442696","labels":["word"]},"end":{"id":"442558","labels":["description"]}}
{"id":"442596","type":"relationship","label":"USE","start":{"id":"442692","labels":["people"]},"end":{"id":"442600","labels":["word"]}}
{"id":"442597","type":"relationship","label":"IMPLY","start":{"id":"442697","labels":["word"]},"end":{"id":"442716","labels":["description"]}}
{"id":"442598","type":"relationship","label":"BEING","start":{"id":"442630","labels":["social-status"]},"end":{"id":"442642","labels":["description"]}}
{"id":"442599","type":"relationship","label":"BEING","start":{"id":"442630","labels":["social-status"]},"end":{"id":"442655","labels":["description"]}}
{"id":"442600","type":"relationship","label":"BEING","start":{"id":"442630","labels":["social-status"]},"end":{"id":"442558","labels":["description"]}}
{"id":"442601","type":"relationship","label":"IMPLY","start":{"id":"384441","labels":["word"]},"end":{"id":"442642","labels":["description"]}}
{"id":"442602","type":"relationship","label":"IMPLY","start":{"id":"384442","labels":["word"]},"end":{"id":"442641","labels":["description"]}}
{"id":"442603","type":"relationship","label":"IMPLY","start":{"id":"384442","labels":["word"]},"end":{"id":"442558","labels":["description"]}}
{"id":"442604","type":"relationship","label":"IMPLY","start":{"id":"358941","labels":["word"]},"end":{"id":"442645","labels":["description"]}}
{"id":"442605","type":"relationship","label":"USE","start":{"id":"442627","labels":["think-style"]},"end":{"id":"442574","labels":["word"]}}
{"id":"442606","type":"relationship","label":"OPPOSITE","start":{"id":"442629","labels":["think-style"]},"end":{"id":"442636","labels":["think-style"]}}
{"id":"442608","type":"relationship","label":"IMPLY","start":{"id":"384442","labels":["word"]},"end":{"id":"442642","labels":["description"]}}
{"id":"442609","type":"relationship","label":"IMPLY","start":{"id":"384442","labels":["word"]},"end":{"id":"442655","labels":["description"]}}
{"id":"442610","type":"relationship","label":"IMPLY","start":{"id":"358941","labels":["word"]},"end":{"id":"442658","labels":["description"]}}
{"id":"442611","type":"relationship","label":"IMPLY","start":{"id":"358941","labels":["word"]},"end":{"id":"442659","labels":["description"]}}
{"id":"442613","type":"relationship","label":"IMPLY","start":{"id":"358941","labels":["word"]},"end":{"id":"442671","labels":["description"]}}
{"id":"442614","type":"relationship","label":"IMPLY","start":{"id":"442697","labels":["word"]},"end":{"id":"442561","labels":["description"]}}
{"id":"442615","type":"relationship","label":"IMPLY","start":{"id":"358941","labels":["word"]},"end":{"id":"442672","labels":["description"]}}
{"id":"442616","type":"relationship","label":"IMPLY","start":{"id":"384443","labels":["word"]},"end":{"id":"442665","labels":["description"]}}
{"id":"442617","type":"relationship","label":"BEING","start":{"id":"358942","labels":["people"]},"end":{"id":"442657","labels":["description"]}}
{"id":"442618","type":"relationship","label":"IMPLY","start":{"id":"384441","labels":["word"]},"end":{"id":"442657","labels":["description"]}}
{"id":"442619","type":"relationship","label":"IMPLY","start":{"id":"384441","labels":["word"]},"end":{"id":"442539","labels":["description","people"]}}
{"id":"442620","type":"relationship","label":"USE","start":{"id":"358942","labels":["people"]},"end":{"id":"384441","labels":["word"]}}
{"id":"442621","type":"relationship","label":"IMPLY","start":{"id":"384445","labels":["word"]},"end":{"id":"442660","labels":["description"]}}
{"id":"442622","type":"relationship","label":"IMPLY","start":{"id":"384446","labels":["word"]},"end":{"id":"442561","labels":["description"]}}
{"id":"442623","type":"relationship","label":"IMPLY","start":{"id":"384446","labels":["word"]},"end":{"id":"442664","labels":["description"]}}
{"id":"442624","type":"relationship","label":"IMPLY","start":{"id":"384450","labels":["word"]},"end":{"id":"442649","labels":["description"]}}
{"id":"442625","type":"relationship","label":"IMPLY","start":{"id":"384454","labels":["word"]},"end":{"id":"442625","labels":["mental-state"]}}
{"id":"442626","type":"relationship","label":"CONTAIN","start":{"id":"442593","labels":["word"]},"end":{"id":"384446","labels":["word"]}}
{"id":"442627","type":"relationship","label":"lackOf","start":{"id":"442650","labels":["write-style"]},"end":{"id":"24","labels":["description"]}}
{"id":"442628","type":"relationship","label":"USE","start":{"id":"442692","labels":["people"]},"end":{"id":"442604","labels":["word"]}}
{"id":"442629","type":"relationship","label":"USE","start":{"id":"442692","labels":["people"]},"end":{"id":"442579","labels":["word"]}}
{"id":"442630","type":"relationship","label":"USE","start":{"id":"442692","labels":["people"]},"end":{"id":"442606","labels":["word"]}}
{"id":"442631","type":"relationship","label":"IMPLY","start":{"id":"384443","labels":["word"]},"end":{"id":"442666","labels":["description"]}}
{"id":"442632","type":"relationship","label":"BEING","start":{"id":"358942","labels":["people"]},"end":{"id":"442539","labels":["description","people"]}}
{"id":"442633","type":"relationship","label":"BEING","start":{"id":"442560","labels":["people"]},"end":{"id":"442539","labels":["description","people"]}}
{"id":"442634","type":"relationship","label":"BEING","start":{"id":"442559","labels":["people"]},"end":{"id":"442657","labels":["description"]}}
{"id":"442635","type":"relationship","label":"IMPLY","start":{"id":"384446","labels":["word"]},"end":{"id":"442541","labels":["description"]}}
{"id":"442636","type":"relationship","label":"IMPLY","start":{"id":"384446","labels":["word"]},"end":{"id":"442663","labels":["description"]}}
{"id":"442637","type":"relationship","label":"USE","start":{"id":"442711","labels":["people"]},"end":{"id":"442592","labels":["word"]}}
{"id":"442638","type":"relationship","label":"IMPLY","start":{"id":"384453","labels":["word"]},"end":{"id":"442631","labels":["mental-state"]}}
{"id":"442639","type":"relationship","label":"IMPLY","start":{"id":"442579","labels":["word"]},"end":{"id":"442625","labels":["mental-state"]}}
{"id":"442640","type":"relationship","label":"USE","start":{"id":"442560","labels":["people"]},"end":{"id":"384454","labels":["word"]}}
{"id":"442641","type":"relationship","label":"USE","start":{"id":"442560","labels":["people"]},"end":{"id":"384455","labels":["word"]}}
{"id":"442642","type":"relationship","label":"CONTAIN","start":{"id":"442594","labels":["word"]},"end":{"id":"384445","labels":["word"]}}
{"id":"442643","type":"relationship","label":"CONTAIN","start":{"id":"442594","labels":["word"]},"end":{"id":"442592","labels":["word"]}}
{"id":"442644","type":"relationship","label":"CONTAIN","start":{"id":"442594","labels":["word"]},"end":{"id":"384455","labels":["word"]}}
{"id":"442645","type":"relationship","label":"USE","start":{"id":"442562","labels":["people"]},"end":{"id":"384446","labels":["word"]}}
{"id":"442646","type":"relationship","label":"USE","start":{"id":"442711","labels":["people"]},"end":{"id":"384458","labels":["word"]}}
{"id":"442647","type":"relationship","label":"USE","start":{"id":"442562","labels":["people"]},"end":{"id":"384441","labels":["word"]}}
{"id":"442648","type":"relationship","label":"USE","start":{"id":"442630","labels":["social-status"]},"end":{"id":"442593","labels":["word"]}}
{"id":"442649","type":"relationship","label":"USE","start":{"id":"442563","labels":["people"]},"end":{"id":"442594","labels":["word"]}}
{"id":"442650","type":"relationship","label":"CONTAIN","start":{"id":"442650","labels":["write-style"]},"end":{"id":"401394","labels":["word"]}}
{"id":"442651","type":"relationship","label":"CONTAIN","start":{"id":"442650","labels":["write-style"]},"end":{"id":"442584","labels":["word"]}}
{"id":"442652","type":"relationship","label":"CONTAIN","start":{"id":"442650","labels":["write-style"]},"end":{"id":"384457","labels":["word"]}}
{"id":"442653","type":"relationship","label":"CONTAIN","start":{"id":"442650","labels":["write-style"]},"end":{"id":"384447","labels":["word"]}}
{"id":"442654","type":"relationship","label":"CONTAIN","start":{"id":"442650","labels":["write-style"]},"end":{"id":"442593","labels":["word"]}}
{"id":"442655","type":"relationship","label":"IMPLY","start":{"id":"442650","labels":["write-style"]},"end":{"id":"442670","labels":["description"]}}
{"id":"442656","type":"relationship","label":"IMPLY","start":{"id":"442650","labels":["write-style"]},"end":{"id":"442642","labels":["description"]}}
{"id":"442657","type":"relationship","label":"IMPLY","start":{"id":"442650","labels":["write-style"]},"end":{"id":"442631","labels":["mental-state"]}}
{"id":"442658","type":"relationship","label":"IMPLY","start":{"id":"442650","labels":["write-style"]},"end":{"id":"442665","labels":["description"]}}
{"id":"442659","type":"relationship","label":"lackOf","start":{"id":"442650","labels":["write-style"]},"end":{"id":"442671","labels":["description"]}}
{"id":"442660","type":"relationship","label":"IMPLY","start":{"id":"442651","labels":["write-style"]},"end":{"id":"442567","labels":["description"]}}
{"id":"442661","type":"relationship","label":"CONTAIN","start":{"id":"442651","labels":["write-style"]},"end":{"id":"442596","labels":["word"]}}
{"id":"442662","type":"relationship","label":"CONTAIN","start":{"id":"442651","labels":["write-style"]},"end":{"id":"442595","labels":["word"]}}
{"id":"442663","type":"relationship","label":"CONTAIN","start":{"id":"442651","labels":["write-style"]},"end":{"id":"384456","labels":["word"]}}
{"id":"442664","type":"relationship","label":"CONTAIN","start":{"id":"442651","labels":["write-style"]},"end":{"id":"442597","labels":["word"]}}
{"id":"442665","type":"relationship","label":"CONTAIN","start":{"id":"442651","labels":["write-style"]},"end":{"id":"442598","labels":["word"]}}
{"id":"442666","type":"relationship","label":"CONTAIN","start":{"id":"442637","labels":["write-style"]},"end":{"id":"384441","labels":["word"]}}
{"id":"442667","type":"relationship","label":"CONTAIN","start":{"id":"442637","labels":["write-style"]},"end":{"id":"384443","labels":["word"]}}
{"id":"442668","type":"relationship","label":"USE","start":{"id":"442562","labels":["people"]},"end":{"id":"401394","labels":["word"]}}
{"id":"442669","type":"relationship","label":"IMPLY","start":{"id":"442651","labels":["write-style"]},"end":{"id":"442671","labels":["description"]}}
{"id":"442670","type":"relationship","label":"IMPLY","start":{"id":"442651","labels":["write-style"]},"end":{"id":"442648","labels":["description"]}}
{"id":"442671","type":"relationship","label":"CONTAIN","start":{"id":"442651","labels":["write-style"]},"end":{"id":"442568","labels":["word"]}}
{"id":"442672","type":"relationship","label":"CONTAIN","start":{"id":"442651","labels":["write-style"]},"end":{"id":"442599","labels":["word"]}}
{"id":"442673","type":"relationship","label":"CONTAIN","start":{"id":"442637","labels":["write-style"]},"end":{"id":"358941","labels":["word"]}}
{"id":"442674","type":"relationship","label":"CONTAIN","start":{"id":"442637","labels":["write-style"]},"end":{"id":"384444","labels":["word"]}}
{"id":"442675","type":"relationship","label":"CONTAIN","start":{"id":"442637","labels":["write-style"]},"end":{"id":"442600","labels":["word"]}}
{"id":"442676","type":"relationship","label":"CONTAIN","start":{"id":"442637","labels":["write-style"]},"end":{"id":"384450","labels":["word"]}}
{"id":"442677","type":"relationship","label":"IMPLY","start":{"id":"442637","labels":["write-style"]},"end":{"id":"442661","labels":["description"]}}
{"id":"442678","type":"relationship","label":"IMPLY","start":{"id":"442637","labels":["write-style"]},"end":{"id":"442660","labels":["description"]}}
{"id":"442679","type":"relationship","label":"BEING","start":{"id":"442539","labels":["description","people"]},"end":{"id":"442653","labels":["team-identity"]}}
{"id":"442680","type":"relationship","label":"NEED","start":{"id":"29","labels":["word"]},"end":{"id":"442633","labels":["need"]}}
{"id":"442681","type":"relationship","label":"BEING","start":{"id":"442539","labels":["description","people"]},"end":{"id":"442654","labels":["team-identity"]}}
{"id":"442682","type":"relationship","label":"USE","start":{"id":"442628","labels":["think-style"]},"end":{"id":"384456","labels":["word"]}}
{"id":"442684","type":"relationship","label":"NEED","start":{"id":"27","labels":["word"]},"end":{"id":"442632","labels":["need"]}}
{"id":"442685","type":"relationship","label":"USE","start":{"id":"442627","labels":["think-style"]},"end":{"id":"384446","labels":["word"]}}
{"id":"442686","type":"relationship","label":"USE","start":{"id":"442627","labels":["think-style"]},"end":{"id":"384452","labels":["word"]}}
{"id":"442687","type":"relationship","label":"USE","start":{"id":"442627","labels":["think-style"]},"end":{"id":"442584","labels":["word"]}}
{"id":"442688","type":"relationship","label":"CONTAIN","start":{"id":"442637","labels":["write-style"]},"end":{"id":"384442","labels":["word"]}}
{"id":"442689","type":"relationship","label":"USE","start":{"id":"442629","labels":["think-style"]},"end":{"id":"384452","labels":["word"]}}
{"id":"442690","type":"relationship","label":"USE","start":{"id":"442627","labels":["think-style"]},"end":{"id":"442570","labels":["word"]}}
{"id":"442691","type":"relationship","label":"OPPOSITE","start":{"id":"442627","labels":["think-style"]},"end":{"id":"442634","labels":["think-style"]}}
{"id":"442696","type":"relationship","label":"BEING","start":{"id":"442638","labels":["emotion"]},"end":{"id":"442648","labels":["description"]}}
{"id":"442697","type":"relationship","label":"BEING","start":{"id":"442638","labels":["emotion"]},"end":{"id":"442690","labels":["description"]}}
{"id":"442698","type":"relationship","label":"USE","start":{"id":"442629","labels":["think-style"]},"end":{"id":"442596","labels":["word"]}}
{"id":"442699","type":"relationship","label":"USE","start":{"id":"442629","labels":["think-style"]},"end":{"id":"442596","labels":["word"]}}